MDPlus/__init__.py
MDPlus/core.py
MDPlus/fastfitting.cpython-36m-darwin.so
MDPlus/utils.py
MDPlus/analysis/__init__.py
MDPlus/analysis/mapping.py
MDPlus/analysis/pca.py
pcazip/__init__.py
pcazip/_version.py
pcazip/pypcaunzip.py
pcazip/pypcazip.py
pcazip/pypczclust.py
pcazip/pypczcomp.py
pcazip/pypczdump.py
pyPcazip-2.0.7.data/scripts/pyPcaunzip
pyPcazip-2.0.7.data/scripts/pyPcazip
pyPcazip-2.0.7.data/scripts/pyPczclust
pyPcazip-2.0.7.data/scripts/pyPczcomp
pyPcazip-2.0.7.data/scripts/pyPczdump
pyPcazip-2.0.7.data/scripts/pyPczplot
pyPcazip-2.0.7.dist-info/METADATA
pyPcazip-2.0.7.dist-info/RECORD
pyPcazip-2.0.7.dist-info/WHEEL
pyPcazip-2.0.7.dist-info/top_level.txt
