Metadata-Version: 2.1
Name: pyPcazip
Version: 2.0.7
Summary: PCA-based molecular dynamics trajectory file compression and analysis.
Home-page: https://bitbucket.org/ramonbsc/pypcazip/overview
Author: The University of Nottingham & BSC
Author-email: charles.laughton@nottingham.ac.uk
License: BSD license.
Download-URL: https://bitbucket.org/ramonbsc/pypcazip/get/2.0.7.tar.gz
Platform: UNKNOWN
Classifier: Development Status :: 5 - Production/Stable
Classifier: Intended Audience :: Science/Research
Classifier: Environment :: Console
Classifier: License :: OSI Approved :: BSD License
Classifier: Programming Language :: Python
Classifier: Programming Language :: Python :: 2
Classifier: Programming Language :: Python :: 2.7
Classifier: Programming Language :: Python :: 3
Classifier: Programming Language :: Python :: 3.4
Classifier: Programming Language :: Python :: 3.5
Classifier: Topic :: Scientific/Engineering
Classifier: Operating System :: MacOS :: MacOS X
Classifier: Operating System :: POSIX
Classifier: Operating System :: Unix
Requires-Dist: numpy
Requires-Dist: scipy
Requires-Dist: cython
Requires-Dist: mdtraj
Requires-Dist: argparse
Requires-Dist: six
Requires-Dist: networkx
Requires-Dist: pandas
